payjoin/__init__.py
payjoin/libpayjoin_ffi.dylib
payjoin/libpayjoin_ffi.so
payjoin/payjoin_ffi.dll
payjoin/payjoin_ffi.py
payjoin-0.1.0.dev0.dist-info/METADATA
payjoin-0.1.0.dev0.dist-info/WHEEL
payjoin-0.1.0.dev0.dist-info/top_level.txt
payjoin-0.1.0.dev0.dist-info/RECORD
