Metadata-Version: 2.1
Name: payjoin
Version: 0.1.0.dev0
Summary: The Python language bindings for the Payjoin Dev Kit
Home-page: https://LtbL.io
Author: BitcoinZavior
Author-email: BitcoinZavior@GMail.Com
License: MIT or Apache 2.0
